extensions/__init__.py
extensions/emoji.py
hydrorollcore-1.0.3.dist-info/METADATA
hydrorollcore-1.0.3.dist-info/WHEEL
hydrorollcore-1.0.3.dist-info/entry_points.txt
hydrorollcore-1.0.3.dist-info/licenses/LICENSE
hydrorollcore/__init__.py
hydrorollcore/cli.py
hydrorollcore/config.py
hydrorollcore/core.py
hydrorollcore/exceptions.py
hydrorollcore/log.py
hydrorollcore/rule.py
hydrorollcore/typing.py
hydrorollcore/utils.py
plugins/__init__.py
plugins/blog/__init__.py
plugins/blog/author.py
plugins/blog/config.py
plugins/blog/plugin.py
plugins/blog/readtime/__init__.py
plugins/blog/readtime/parser.py
plugins/blog/structure/__init__.py
plugins/blog/structure/config.py
plugins/blog/structure/markdown.py
plugins/blog/structure/options.py
plugins/blog/templates/__init__.py
plugins/group/__init__.py
plugins/group/config.py
plugins/group/plugin.py
plugins/info/__init__.py
plugins/info/config.py
plugins/info/plugin.py
plugins/offline/__init__.py
plugins/offline/config.py
plugins/offline/plugin.py
plugins/search/__init__.py
plugins/search/config.py
plugins/search/plugin.py
plugins/social/__init__.py
plugins/social/config.py
plugins/social/plugin.py
plugins/tags/__init__.py
plugins/tags/config.py
plugins/tags/plugin.py
templates/.icons/logo.afdesign
templates/.icons/logo.svg
templates/404.html
templates/__init__.py
templates/assets/images/favicon.png
templates/assets/javascripts/_/index.ts
templates/assets/javascripts/browser/document/index.ts
templates/assets/javascripts/browser/element/_/.eslintrc
templates/assets/javascripts/browser/element/_/index.ts
templates/assets/javascripts/browser/element/focus/index.ts
templates/assets/javascripts/browser/element/index.ts
templates/assets/javascripts/browser/element/offset/_/index.ts
templates/assets/javascripts/browser/element/offset/content/index.ts
templates/assets/javascripts/browser/element/offset/index.ts
templates/assets/javascripts/browser/element/size/_/index.ts
templates/assets/javascripts/browser/element/size/content/index.ts
templates/assets/javascripts/browser/element/size/index.ts
templates/assets/javascripts/browser/element/visibility/index.ts
hydrorollcore-1.0.3.dist-info/RECORD
